odoo/addons/ssi_hr_leave_request_batch/README.rst
odoo/addons/ssi_hr_leave_request_batch/__init__.py
odoo/addons/ssi_hr_leave_request_batch/__manifest__.py
odoo/addons/ssi_hr_leave_request_batch/data/approval_template_data.xml
odoo/addons/ssi_hr_leave_request_batch/data/ir_sequence_data.xml
odoo/addons/ssi_hr_leave_request_batch/data/policy_template_data.xml
odoo/addons/ssi_hr_leave_request_batch/data/sequence_template_data.xml
odoo/addons/ssi_hr_leave_request_batch/models/__init__.py
odoo/addons/ssi_hr_leave_request_batch/models/hr_leave.py
odoo/addons/ssi_hr_leave_request_batch/models/hr_leave_request_batch.py
odoo/addons/ssi_hr_leave_request_batch/security/ir.model.access.csv
odoo/addons/ssi_hr_leave_request_batch/security/ir_module_category_data.xml
odoo/addons/ssi_hr_leave_request_batch/security/ir_rule_data.xml
odoo/addons/ssi_hr_leave_request_batch/security/res_group_data.xml
odoo/addons/ssi_hr_leave_request_batch/static/description/icon.png
odoo/addons/ssi_hr_leave_request_batch/views/hr_leave_request_batch_view.xml
odoo/addons/ssi_hr_leave_request_batch/views/hr_leave_views.xml
odoo14_addon_ssi_hr_leave_request_batch-14.0.1.3.0.dist-info/METADATA
odoo14_addon_ssi_hr_leave_request_batch-14.0.1.3.0.dist-info/WHEEL
odoo14_addon_ssi_hr_leave_request_batch-14.0.1.3.0.dist-info/top_level.txt
odoo14_addon_ssi_hr_leave_request_batch-14.0.1.3.0.dist-info/RECORD
